lab3/final_ed/firhls.v
//////////////////////////////////////////////////////////////////////////////////
// Company: 
// Engineer: 
// 
// Create Date: 10/06/2023 09:56:59 AM
// Design Name: 
// Module Name: fir_lite_slave
// Project Name: 
// Target Devices: 
// Tool Versions: 
// Description: 
// 
// Dependencies: 
// 
// Revision:
// Revision 0.01 - File Created
// Additional Comments:
// 
//////////////////////////////////////////////////////////////////////////////////

module fir #(
    parameter C_S_AXI_ADDR_WIDTH = 12,
    parameter C_S_AXI_DATA_WIDTH = 32
)(
    input wire ACLK,
    input wire ARESET,

    input wire [C_S_AXI_ADDR_WIDTH-1:0] AWADDR,
    input wire AWVALID,
    output wire AWREADY,

    input wire [C_S_AXI_DATA_WIDTH-1:0] WDATA,
    input wire WVALID,
    output wire WREADY,

    input wire [C_S_AXI_ADDR_WIDTH-1:0] ARADDR,
    input wire ARVALID,
    output wire ARREADY,

    output wire [C_S_AXI_DATA_WIDTH-1:0] RDATA,
    output wire RVALID,
    input wire RREADY,

    output wire [3:0] Tap_WE,
    output wire Tap_EN,
    output wire [C_S_AXI_DATA_WIDTH-1:0] Tap_Di,
    output wire [C_S_AXI_ADDR_WIDTH-1:0] Tap_A,
    input wire [C_S_AXI_DATA_WIDTH-1:0] Tap_Do,

    input wire SS_tvalid,
    input wire [C_S_AXI_DATA_WIDTH-1:0] SS_tdata,
    input wire SS_tlast,
    output wire SS_tready,

    input wire SM_tready,
    output wire SM_tvalid,
    output wire [C_S_AXI_DATA_WIDTH-1:0] SM_tdata,
    output wire SM_tlast,

    output wire [3:0] Data_WE,
    output wire Data_EN,
    output wire [C_S_AXI_DATA_WIDTH-1:0] Data_Di,
    output wire [C_S_AXI_ADDR_WIDTH-1:0] Data_A,
    input wire [C_S_AXI_DATA_WIDTH-1:0] Data_Do
);

    localparam
        ADDR_AP_CTRL = 12'h00,
        ADDR_datalength = 12'h10,
        ADDR_tapparameters = 12'hFF;
    
    // Output signal use reg
    reg aw_ready; 
    reg w_ready; 
    reg ar_ready; 
    reg [C_S_AXI_DATA_WIDTH-1:0] r_data;
    reg [C_S_AXI_ADDR_WIDTH-1:0] aw_addr;
    reg r_valid; 
    reg [3:0] tapwe;
    reg tapen;
    reg [C_S_AXI_DATA_WIDTH-1:0] tapdi;
    reg [C_S_AXI_ADDR_WIDTH-1:0] tapa;
    reg [3:0] datawe;
    reg dataen;
    reg [C_S_AXI_DATA_WIDTH-1:0] datadi;
    reg [C_S_AXI_ADDR_WIDTH-1:0] dataa;
    reg smtvalid;
    reg smtlast;
    assign SM_tlast = smtlast;
    assign SM_tdata = yout;
    assign SM_tvalid = smtvalid;
    assign Tap_WE = tapwe;
    assign Tap_EN = tapen;
    assign Tap_Di = tapdi;
    assign Tap_A = tapa;
    assign Data_WE = datawe;
    assign Data_EN = dataen;
    assign Data_Di = datadi;
    assign Data_A = dataa;
    assign AWREADY = aw_ready;
    assign WREADY = w_ready;
    assign ARREADY = ar_ready;
    assign RVALID = r_valid;
    assign RDATA = r_data;

    // BRAM 0 state
    reg bramstate;
    always @(posedge ACLK) begin
        if (ARESET == 1'b0) begin
            bramstate <= 0;
            dataa <= 12'h0;
        end else begin
            if (bramstate == 1'b0) begin
                if (dataa == 12'h28) begin
                    datadi <= 32'h00;
                    dataa <= 12'h00;
                    bramstate <= 1'b1;
                end else begin
                    datadi <= 32'h00;
                    dataa <= dataa + 12'h04;
                end
            end
        end
    end

    // Decide the last input and last output state
    reg last;
    always @(posedge ACLK) begin
        if (ARESET == 1'b0) begin
            last <= 0;
        end else begin
            if (SS_tlast && sstready) begin
                last <= 1'b1;
            end
            if (last && smtvalid) begin
                int_task_ap_done <= 1'b1;
                int_ap_idle <= 1'b1;
                smtvalid <= 1'b0;
            end
        end
    end

    // FIR calculation
    reg [C_S_AXI_DATA_WIDTH-1:0] ymult;
    reg [C_S_AXI_DATA_WIDTH-1:0] yout;
    always @(posedge ACLK) begin
        if (ARESET == 1'b0) begin
            smtvalid <= 1'b0;
            yout <= 32'h0;
            ymult <= 32'h0;            
            smtlast <= 1'b0;
        end else begin
        if (firstate) begin
            case (tapa)
                12'h00: begin
                    ymult <= Tap_Do * Data_Do;
                    dataa <= (dataa == 12'h28) ? 12'h00 : dataa + 12'h04;
                    tapa <= tapa + 12'h04;
                end
                12'h04: begin
                    yout <= ymult;
                    dataa <= (dataa == 12'h28) ? 12'h00 : dataa + 12'h04;
                    ymult <= Tap_Do * Data_Do;
                    tapa <= tapa + 12'h04;
                end
                12'h28: begin
                    ymult <= Tap_Do * Data_Do;
                    yout <= ymult + yout;
                    tapa <= tapa + 12'h04;
                end
                12'h2c: begin
                    firstate <= 1'b0;
                    smtvalid <= 1'b1;
                    tapa <= 12'h00;
                    yout <= ymult + yout;
                    if (~last)
                    sstready <= 1'b1;
                end
                default: begin
                    ymult <= Tap_Do * Data_Do;
                    yout <= ymult + yout;
                    dataa <= (dataa == 12'h28) ? 12'h00 : dataa + 12'h04;
                    tapa <= tapa + 12'h04;
                end
            endcase
        end
      end
    end

    // Xin
    reg sstready = 0;
    assign SS_tready = sstready;
    reg firstate;
    reg [C_S_AXI_ADDR_WIDTH-1:0] data_addr = 12'h20;
    always @(posedge ACLK) begin
        if (ARESET == 1'b0) begin
            sstready <= 1'b0;
            firstate <= 1'b0;
        end else if (SS_tvalid && int_ap_start) begin
            sstready <= 1'b1;
            tapa <= 12'h00;
            dataa <= 12'h00;
            int_ap_start <= 1'b0;
        end else if (sstready && SS_tvalid) begin
            smtvalid <= 1'b0;
            tapa <= 12'h00;
            datadi <= SS_tdata;
            datawe <= 4'b1111;
            sstready <= 1'b0;
            firstate <= 1'b1;
        end else if (bramstate == 1'b0) begin
            datawe <= 4'b1111;
        end else begin
            datawe <= 4'b0;
        end
    end

    // Produce tapen dataen
    always @(posedge ACLK) begin
        if (ARESET == 1'b0) begin
            tapen <= 1'b0;
            dataen <= 1'b0;
        end else begin
            tapen <= 1'b1;
            dataen <= 1'b1;
        end
    end

    // Produce tapwe
    always @(posedge ACLK) begin
        if (ARESET == 1'b0) begin
            tapwe <= 4'b0;
        end else begin
            if ((AWADDR == 12'h0) || (AWADDR == ADDR_datalength)) begin
                tapwe <= 4'b0;
            end else if (~aw_ready && AWVALID && ~w_ready && WVALID) begin
                tapwe <= 4'b1111;
            end else begin
                tapwe <= 4'b0;
            end
        end
    end

    // AXI write
    // Produce awready
    always @(posedge ACLK) begin
        if (ARESET == 1'b0) begin
            aw_ready <= 1'b0;
        end else begin
            if (~aw_ready && AWVALID && WVALID) begin
                aw_ready <= ~aw_ready;
            end else begin
                aw_ready <= 1'b0;
            end
        end
    end

    // Produce wready
    always @(posedge ACLK) begin
        if (ARESET == 1'b0) begin
            w_ready <= 1'b0;
        end else begin
            if (~w_ready && WVALID && AWVALID) begin
                w_ready <= ~w_ready;
            end else begin
                w_ready <= 1'b0;
            end
        end
    end

    // BRAM address
    always @(posedge ACLK) begin
        if (AWVALID == 1'b1) begin
            case (AWADDR)
                12'h20: tapa <= 12'h00;
                12'h24: tapa <= 12'h04;
                12'h28: tapa <= 12'h08;
                12'h2c: tapa <= 12'h0c;
                12'h30: tapa <= 12'h10;
                12'h34: tapa <= 12'h14;
                12'h38: tapa <= 12'h18;
                12'h3c: tapa <= 12'h1c;
                12'h40: tapa <= 12'h20;
                12'h44: tapa <= 12'h24;
                12'h48: tapa <= 12'h28;
                default:tapa <= 12'h00;
            endcase
        end
    end

    always @(negedge ACLK) begin
        if (ARVALID == 1'b1) begin
            if ((ARADDR != 12'h0) && (ARADDR != ADDR_datalength)) begin
                case (ARADDR)
                    12'h20: tapa <= 12'h00;
                    12'h24: tapa <= 12'h04;
                    12'h28: tapa <= 12'h08;
                    12'h2c: tapa <= 12'h0c;
                    12'h30: tapa <= 12'h10;
                    12'h34: tapa <= 12'h14;
                    12'h38: tapa <= 12'h18;
                    12'h3c: tapa <= 12'h1c;
                    12'h40: tapa <= 12'h20;
                    12'h44: tapa <= 12'h24;
                    12'h48: tapa <= 12'h28;
                    default:tapa <= 12'h00;
                endcase
            end
        end
    end

    reg [C_S_AXI_DATA_WIDTH-1:0] data_length;
    // Write in
    always @(posedge ACLK) begin
        if (ARESET == 1'b0) begin
            data_length <= 0;
        end else if (~aw_ready && AWVALID && ~w_ready && WVALID) begin
            case (AWADDR)
                ADDR_AP_CTRL: begin
                    if (WDATA == 32'h0000_0001)
                    int_ap_start <= 1'b1;
                    tapdi <= 0;
                end
                ADDR_datalength: begin
                    data_length <= WDATA;
                    tapdi <= 0;
                end
                default: begin
                    tapdi <= WDATA;
                end
            endcase
        end
    end

    // AXI READ
    // Produce arready
    always @(posedge ACLK) begin
        if (ARESET == 1'b0) begin
            ar_ready <= 1'b0;
        end else begin
            if (~ar_ready & ARVALID) begin
                ar_ready <= ~ar_ready;
            end else begin
                if (r_valid)
                    ar_ready <= ~ar_ready;
            end
        end
    end

    // Produce rvalid
    // Should check if arready is in front
    // Read data
    reg rvalidstate;
    reg int_ap_start;
    reg int_task_ap_done;
    reg int_ap_idle;
    always @(posedge ACLK) begin
        if (ARESET == 1'b0) begin
            r_data <= 0;
            int_task_ap_done <= 1'b0;
            int_ap_idle <= 1'b0;
            r_valid <= 0;
        end else if (ar_ready && ~r_valid && ARVALID) begin
            rvalidstate <= ~rvalidstate;
        end else if (RREADY && r_valid) begin
            r_valid <= 1'b0;
        end
    end
    always @(posedge ACLK) begin
        if (ARESET == 1'b0) begin
            rvalidstate <= 1'b0;
        end else begin
            if (rvalidstate) begin
                rvalidstate <= ~rvalidstate;
                r_valid <= ~r_valid;
                case (ARADDR)
                    ADDR_AP_CTRL: begin
                        r_data[0] <= int_ap_start;
                        r_data[1] <= int_task_ap_done;
                        r_data[2] <= int_ap_idle;
                    end
                    ADDR_datalength: begin
                        r_data <= data_length;
                    end
                    default: begin
                        r_data <= Tap_Do;
                    end
                endcase
            end
        end
    end
endmodule

lab3/final_ed/tb.v
`timescale 1ns / 1ps
//////////////////////////////////////////////////////////////////////////////////
// Company: 
// Engineer: 
// 
// Create Date: 08/20/2023 10:38:55 AM
// Design Name: 
// Module Name: fir_tb
// Project Name: 
// Target Devices: 
// Tool Versions: 
// Description: 
// 
// Dependencies: 
// 
// Revision:
// Revision 0.01 - File Created
// Additional Comments:
// 
//////////////////////////////////////////////////////////////////////////////////


module fir_tb
#(  parameter pADDR_WIDTH = 12,
    parameter pDATA_WIDTH = 32,
    parameter Tape_Num    = 11,
    parameter Data_Num    = 600
)();
    wire                        awready;
    wire                        wready;
    reg                         awvalid;
    reg   [(pADDR_WIDTH-1): 0]  awaddr;
    reg                         wvalid;
    reg signed [(pDATA_WIDTH-1) : 0] wdata;
    wire                        arready;
    reg                         rready;
    reg                         arvalid;
    reg         [(pADDR_WIDTH-1): 0] araddr;
    wire                            rvalid;
    wire signed [(pDATA_WIDTH-1): 0] rdata;


    reg                         axis_clk;
    reg                         axis_rst_n;

// ram for tap
    wire                   [3:0]tap_WE;
    wire                     tap_EN;
    wire [(pDATA_WIDTH-1):0] tap_Di;
    wire [(pADDR_WIDTH-1):0] tap_A;
    wire [(pDATA_WIDTH-1):0] tap_Do;

// ram for data RAM
    wire [3:0]               data_WE;
    wire                     data_EN;
    wire [(pDATA_WIDTH-1):0] data_Di;
    wire [(pADDR_WIDTH-1):0] data_A;
    wire [(pDATA_WIDTH-1):0] data_Do;
    
    reg                         ss_tvalid;
    reg signed [(pDATA_WIDTH-1) : 0] ss_tdata;
    reg                         ss_tlast;
    wire                        ss_tready;
    wire signed [(pDATA_WIDTH-1): 0] y;
    wire signed [(pDATA_WIDTH-1): 0] ym;

    reg                         sm_tready;
    wire                        sm_tvalid;
    wire signed [(pDATA_WIDTH-1) : 0] sm_tdata;
    wire                        sm_tlast;



      fir fir_DUT(
        .AWREADY(awready),
        .WREADY(wready),
        .AWVALID(awvalid),
        .AWADDR(awaddr),
        .WVALID(wvalid),
        .WDATA(wdata),
        .ARREADY(arready),
        .RREADY(rready),
        .ARVALID(arvalid),
        .ARADDR(araddr),
        .RVALID(rvalid),
        .RDATA(rdata),
        // ram for tap
        .Tap_WE(tap_WE),
        .Tap_EN(tap_EN),
        .Tap_Di(tap_Di),
        .Tap_A(tap_A),
        .Tap_Do(tap_Do),

        // ram for data
        .Data_WE(data_WE),
        .Data_EN(data_EN),
        .Data_Di(data_Di),
        .Data_A(data_A),
        .Data_Do(data_Do),
        
        
        .SS_tvalid(ss_tvalid),
        .SS_tdata(ss_tdata),
        .SS_tlast(ss_tlast),
        .SS_tready(ss_tready),
        
        .SM_tready(sm_tready),
        .SM_tvalid(sm_tvalid),
        .SM_tdata(sm_tdata),
        .SM_tlast(sm_tlast),
        
        
        .ACLK(axis_clk),
        .ARESET(axis_rst_n)

        );
    
    // RAM for tap
    bram11 tap_RAM (
        .CLK(axis_clk),
        .WE(tap_WE),
        .EN(tap_EN),
        .Di(tap_Di),
        .A(tap_A),
        .Do(tap_Do)
    );

   bram11 data_RAM(
        .CLK(axis_clk),
        .WE(data_WE),
        .EN(data_EN),
        .Di(data_Di),
        .A(data_A),
        .Do(data_Do)
    );

    initial begin
        axis_clk = 0;
        forever begin
            #5 axis_clk = (~axis_clk);
        end
    end
    
    integer timeout = (1000000);
    initial begin
        while(timeout > 0) begin
            @(posedge axis_clk);
            timeout = timeout - 1;
        end
        $display($time, "Simualtion Hang ....");
        $finish;
    end
    
    reg signed [(pDATA_WIDTH-1):0] Din_list[0:(Data_Num-1)];
    reg signed [(pDATA_WIDTH-1):0] golden_list[0:(Data_Num-1)];
    reg [31:0]  data_length;
    integer Din, golden, input_data, golden_data, m;
    initial begin
        data_length = 0;
        Din = $fopen("/home/ubuntu/samples_triangular_wave.dat","r");
        golden = $fopen("/home/ubuntu/out_gold.dat","r");
        for(m=0;m<Data_Num;m=m+1) begin
            input_data = $fscanf(Din,"%d", Din_list[m]);
            golden_data = $fscanf(golden,"%d", golden_list[m]);
            data_length = data_length + 1;
        end
    end
    
    

    initial begin
        axis_rst_n = 0;
        @(posedge axis_clk); @(posedge axis_clk);
        axis_rst_n = 1;
    end

    reg signed [31:0] coef[0:10]; // fill in coef 
    initial begin
        coef[0]  =  32'd0;
        coef[1]  = -32'd10;
        coef[2]  = -32'd9;
        coef[3]  =  32'd23;
        coef[4]  =  32'd56;
        coef[5]  =  32'd63;
        coef[6]  =  32'd56;
        coef[7]  =  32'd23;
        coef[8]  = -32'd9;
        coef[9]  = -32'd10;
        coef[10] =  32'd0;
    end
integer i;

  initial begin
        $display("------------Start simulation-----------");
        ss_tvalid = 0;
        $display("----Start the data input(AXI-Stream)----");
        for(i=0;i<(data_length-1);i=i+1) begin
            ss_tlast = 0; ss(Din_list[i]);
        end
         config_read_check(12'h00, 32'h00, 32'h0000_000f); 
         arvalid <= 0; 
         ss_tlast = 1; ss(Din_list[(Data_Num-1)]);
      $display("------End the data input(AXI-Stream)------");
 end
    reg error;
    reg status_error;

   initial begin
        error = 0; status_error = 0;
        sm_tready = 1;
        wait (sm_tvalid);
        for(k=0;k <data_length;k=k+1) begin
        sm(golden_list[k],k);
        end
       config_read_check(12'h00, 32'h06, 32'h0000_0002); // check ap_done = 1 (0x00 [bit 1])
       config_read_check(12'h00, 32'h06, 32'h0000_0004);
     arvalid <= 0; // check ap_idle = 1 (0x00 [bit 2])
        if (error == 0 & error_coef == 0) begin
            $display("---------------------------------------------");
            $display("-----------Congratulations! Pass-------------");
        end
        else begin
            $display("--------Simulation Failed---------");
        end
       $finish;
    end
reg error_coef;
integer k;
    initial begin
        error_coef = 0;
        $display("----Start the coefficient input(AXI-lite)----");
        config_write(12'h10, data_length);
        for(k=0; k< Tape_Num; k=k+1) begin
            config_write(12'h20+4*k, coef[k]);
        end
        awvalid <= 0; wvalid <= 0;
        // read-back and check
        $display(" Check Coefficient ...");
            for(k=0; k < Tape_Num; k=k+1) begin
            config_read_check(12'h20+4*k, coef[k], 32'hffffffff);
        end         
        arvalid <= 0;
        $display(" Tape programming done ...");
        $display(" Start FIR");
        @(posedge axis_clk) config_write(12'h00, 32'h0000_0001); // ap_start = 1
         awvalid <= 0; wvalid <= 0;
        $display("----End the coefficient input(AXI-lite)----");
    end



    task config_write;
        input [11:0]    addr;
        input [31:0]    data;
        begin
            awvalid <= 0; wvalid <= 0;
            @(posedge axis_clk);
            awvalid <= 1; awaddr <= addr;
            wvalid  <= 1; wdata <= data;
            @(posedge axis_clk);
            while (!wready) @(posedge axis_clk);
        end
    endtask

    task config_read_check;
        input [11:0]        addr;
        input signed [31:0] exp_data;
        input [31:0]        mask;
        begin
            arvalid <= 0;
            @(posedge axis_clk);
            arvalid <= 1; araddr <= addr;
            rready <= 1;
            @(posedge axis_clk);
            while (!rvalid) @(posedge axis_clk);
            if( (rdata & mask) != (exp_data & mask)) begin
                $display("ERROR: exp = %d, rdata = %d", exp_data, rdata);
                error_coef <= 1;
            end else begin
                $display("OK: exp = %d, rdata = %d", exp_data, rdata);
            end
        end
    endtask
    
        task ss;
        input  signed [31:0] in1;
        begin
            ss_tvalid <= 1;
            ss_tdata  <= in1;
            @(posedge axis_clk);
            while (!ss_tready) begin
                @(posedge axis_clk);
            end
        end
    endtask


    task sm;
        input  signed [31:0] in2; // golden data
        input         [31:0] pcnt; // pattern count
        begin
            sm_tready <= 1;
            @(posedge axis_clk) 
            wait(sm_tvalid);
        
            while(!sm_tvalid) @(posedge axis_clk);
            if (sm_tdata != in2) begin
                $display("[ERROR] [Pattern %d] Golden answer: %d, Your answer: %d", pcnt, in2, sm_tdata);
                error <= 1;
            end
            else begin
                $display("[PASS] [Pattern %d] Golden answer: %d, Your answer: %d", pcnt, in2, sm_tdata);
            end
            @(posedge axis_clk);
        end
    endtask



endmodule


// bram behavior code (can't be synthesis)
// 11 words
module bram11 
(
    CLK,
    WE,
    EN,
    Di,
    Do,
    A
);
    input   wire            CLK;
    input   wire    [3:0]   WE;
    input   wire            EN;
    input   wire    [31:0]  Di;
    output  wire     [31:0]  Do;
    input   wire    [11:0]   A; 

    //  11 words
	reg [31:0] RAM[0:10];
    reg [11:0] r_A;

    always @(posedge CLK) begin
        r_A <= A;
    end

    assign Do = {32{EN}} & RAM[r_A>>2];    // read
    
    reg [31:0] Temp_D;
    always @(posedge CLK) begin
        if(EN) begin
            if(WE[0]) RAM[A>>2][7:0] <= Di[7:0];
            if(WE[1]) RAM[A>>2][15:8] <= Di[15:8];
            if(WE[2]) RAM[A>>2][23:16] <= Di[23:16];
            if(WE[3]) RAM[A>>2][31:24] <= Di[31:24];
        end
    end

endmodule

lab3/sim/fir.vcd
$date
   Thu Oct 12 05:30:31 2023
$end
$version
  2022.1
$end
$timescale
  1ps
$end
$scope module fir_tb $end
$var wire 1 ! awready $end
$var wire 1 " wready $end
$var reg 1 # awvalid $end
$var reg 12 $ awaddr [11:0] $end
$var reg 1 % wvalid $end
$var reg 32 & wdata [31:0] $end
$var wire 1 ' arready $end
$var reg 1 ( rready $end
$var reg 1 ) arvalid $end
$var reg 12 * araddr [11:0] $end
$var wire 1 + rvalid $end
$var wire 32 , rdata [31:0] $end
$var reg 1 - axis_clk $end
$var reg 1 . axis_rst_n $end
$var wire 4 / tap_WE [3:0] $end
$var wire 1 0 tap_EN $end
$var wire 32 1 tap_Di [31:0] $end
$var wire 12 2 tap_A [11:0] $end
$var wire 32 3 tap_Do [31:0] $end
$var wire 4 4 data_WE [3:0] $end
$var wire 1 5 data_EN $end
$var wire 32 6 data_Di [31:0] $end
$var wire 12 7 data_A [11:0] $end
$var wire 32 8 data_Do [31:0] $end
$var reg 1 9 ss_tvalid $end
$var reg 32 : ss_tdata [31:0] $end
$var reg 1 ; ss_tlast $end
$var wire 1 < ss_tready $end
$var wire 32 = y [31:0] $end
$var wire 32 > ym [31:0] $end
$var reg 1 ? sm_tready $end
$var wire 1 @ sm_tvalid $end
$var wire 32 A sm_tdata [31:0] $end
$var wire 1 B sm_tlast $end
$var reg 32 C data_length [31:0] $end
$var integer 32 D Din [31:0] $end
$var integer 32 E golden [31:0] $end
$var integer 32 F input_data [31:0] $end
$var integer 32 G golden_data [31:0] $end
$var integer 32 H m [31:0] $end
$var integer 32 I i [31:0] $end
$var integer 32 J k [31:0] $end
$var reg 1 K error $end
$var reg 1 L status_error $end
$var integer 32 M timeout [31:0] $end
$var reg 1 N error_coef $end
$scope module fir_DUT $end
$var wire 1 O ACLK $end
$var wire 1 P ARESET $end
$var wire 12 Q AWADDR [11:0] $end
$var wire 1 R AWVALID $end
$var wire 1 ! AWREADY $end
$var wire 32 S WDATA [31:0] $end
$var wire 1 T WVALID $end
$var wire 1 " WREADY $end
$var wire 12 U ARADDR [11:0] $end
$var wire 1 V ARVALID $end
$var wire 1 ' ARREADY $end
$var wire 32 , RDATA [31:0] $end
$var wire 1 + RVALID $end
$var wire 1 W RREADY $end
$var wire 4 / Tap_WE [3:0] $end
$var wire 1 0 Tap_EN $end
$var wire 32 1 Tap_Di [31:0] $end
$var wire 12 2 Tap_A [11:0] $end
$var wire 32 3 Tap_Do [31:0] $end
$var wire 1 X SS_tvalid $end
$var wire 32 Y SS_tdata [31:0] $end
$var wire 1 Z SS_tlast $end
$var wire 1 < SS_tready $end
$var wire 1 [ SM_tready $end
$var wire 1 @ SM_tvalid $end
$var wire 32 A SM_tdata [31:0] $end
$var wire 1 B SM_tlast $end
$var wire 4 4 Data_WE [3:0] $end
$var wire 1 5 Data_EN $end
$var wire 32 6 Data_Di [31:0] $end
$var wire 12 7 Data_A [11:0] $end
$var wire 32 8 Data_Do [31:0] $end
$var reg 1 \ aw_ready $end
$var reg 1 ] w_ready $end
$var reg 1 ^ ar_ready $end
$var reg 32 _ r_data [31:0] $end
$var reg 12 ` aw_addr [11:0] $end
$var reg 1 a r_valid $end
$var reg 4 b tapwe [3:0] $end
$var reg 1 c tapen $end
$var reg 32 d tapdi [31:0] $end
$var reg 12 e tapa [11:0] $end
$var reg 4 f datawe [3:0] $end
$var reg 1 g dataen $end
$var reg 32 h datadi [31:0] $end
$var reg 12 i dataa [11:0] $end
$var reg 1 j smtvalid $end
$var reg 1 k smtlast $end
$var reg 1 l bramstate $end
$var reg 1 m last $end
$var reg 32 n ymult [31:0] $end
$var reg 32 o yout [31:0] $end
$var reg 1 p sstready $end
$var reg 1 q firstate $end
$var reg 12 r data_addr [11:0] $end
$var reg 32 s data_length [31:0] $end
$var reg 1 t rvalidstate $end
$var reg 1 u int_ap_start $end
$var reg 1 v int_task_ap_done $end
$var reg 1 w int_ap_idle $end
$upscope $end
$scope module tap_RAM $end
$var wire 1 x CLK $end
$var wire 4 / WE [3:0] $end
$var wire 1 0 EN $end
$var wire 32 1 Di [31:0] $end
$var wire 32 3 Do [31:0] $end
$var wire 12 2 A [11:0] $end
$var reg 12 y r_A [11:0] $end
$var reg 32 z Temp_D [31:0] $end
$upscope $end
$scope module data_RAM $end
$var wire 1 { CLK $end
$var wire 4 4 WE [3:0] $end
$var wire 1 5 EN $end
$var wire 32 6 Di [31:0] $end
$var wire 32 8 Do [31:0] $end
$var wire 12 7 A [11:0] $end
$var reg 12 | r_A [11:0] $end
$var reg 32 } Temp_D [31:0] $end
$upscope $end
$scope task config_write $end
$var reg 12 ~ addr [11:0] $end
$var reg 32 !! data [31:0] $end
$upscope $end
$scope task config_read_check $end
$var reg 12 "! addr [11:0] $end
$var reg 32 #! exp_data [31:0] $end
$var reg 32 $! mask [31:0] $end
$upscope $end
$scope task ss $end
$var reg 32 %! in1 [31:0] $end
$upscope $end
$scope task sm $end
$var reg 32 &! in2 [31:0] $end
$var reg 32 '! pcnt [31:0] $end
$upscope $end
$upscope $end
$enddefinitions $end
#0
$dumpvars
x!
b1001011000 !!
x"
bx "!
0#
bx #!
bx $
bx $!
0%
bx %!
bx &
bx &!
x'
bx '!
x(
x)
bx *
x+
bx ,
0-
0.
bx /
x0
bx 1
bx 2
bx 3
bx 4
x5
bx 6
bx 7
bx 8
19
bx :
0;
0<
bz =
bz >
1?
x@
bx A
xB
b1001011000 C
b0 D
b0 E
b11111111111111111111111111111111 F
b11111111111111111111111111111111 G
b1001011000 H
b0 I
bx J
0K
0L
b11110100001001000000 M
0N
0O
0P
bx Q
0R
bx S
0T
bx U
xV
xW
1X
bx Y
0Z
1[
x\
x]
x^
bx _
bx `
xa
bx b
xc
bx d
bx e
bx f
xg
bx h
bx i
xj
xk
xl
xm
bx n
bx o
0p
xq
b100000 r
bx s
xt
xu
xv
xw
0x
bx y
bx z
0{
bx |
bx }
b10000 ~
$end
#5000
0!
0"
1#
b10000 $
1%
b1001011000 &
0'
0+
b0 ,
1-
b0 /
00
b0 3
05
b0 7
b0 8
0@
b0 A
0B
b11110100001000111111 M
1O
b10000 Q
1R
b1001011000 S
1T
0\
0]
0^
b0 _
0a
b0 b
0c
0g
b0 i
0j
0k
0l
0m
b0 n
b0 o
0p
0q
b0 s
0t
0v
0w
1x
bx y
1{
bx |
#10000
0-
0O
0x
0{
#15000
1!
1"
1-
1.
10
b0 1
b0 2
bx 3
b1111 4
15
b0 6
b100 7
bx 8
b11110100001000111110 M
1O
1P
1\
1]
b0 b
1c
b0 d
b0 e
b1111 f
1g
b0 h
b100 i
b1001011000 s
1x
bx y
1{
b0 |
#20000
0-
0O
0x
0{
#25000
0!
b0 !!
0"
0#
0%
1-
bx 3
b1000 7
b0 8
b0 J
b11110100001000111101 M
1O
0R
0T
0\
0]
b0 b
1c
b0 e
b1111 f
1g
b0 h
b1000 i
1x
b0 y
1{
b100 |
b100000 ~
#30000
0-
0O
0x
0{
#35000
1#
b100000 $
1%
b0 &
1-
b1100 7
b0 8
b11110100001000111100 M
1O
b100000 Q
1R
b0 S
1T
0\
0]
b0 b
1c
b1111 f
1g
b0 h
b1100 i
1x
b0 y
1{
b1000 |
#40000
0-
0O
0x
0{
#45000
1!
1"
1-
b1111 /
b10000 7
b0 8
b11110100001000111011 M
1O
1\
1]
b1111 b
1c
b0 d
b0 e
b1111 f
1g
b0 h
b10000 i
1x
b0 y
1{
b1100 |
#50000
0-
0O
0x
0{
#55000
0!
b11111111111111111111111111110110 !!
0"
0#
0%
1-
b0 /
b0 3
b10100 7
b0 8
b1 J
b11110100001000111010 M
1O
0R
0T
0\
0]
b0 b
1c
b0 e
b1111 f
1g
b0 h
b10100 i
1x
b0 y
1{
b10000 |
b100100 ~
#60000
0-
0O
0x
0{
#65000
1#
b100100 $
1%
b11111111111111111111111111110110 &
1-
b11000 7
b0 8
b11110100001000111001 M
1O
b100100 Q
1R
b11111111111111111111111111110110 S
1T
0\
0]
b0 b
1c
b1111 f
1g
b0 h
b11000 i
1x
b0 y
1{
b10100 |
#70000
0-
0O
0x
0{
#75000
1!
1"
1-
b1111 /
b11111111111111111111111111110110 1
b100 2
b11100 7
b0 8
b11110100001000111000 M
1O
1\
1]
b1111 b
1c
b11111111111111111111111111110110 d
b100 e
b1111 f
1g
b0 h
b11100 i
1x
b0 y
1{
b11000 |
#80000
0-
0O
0x
0{
#85000
0!
b11111111111111111111111111110111 !!
0"
0#
0%
1-
b0 /
b11111111111111111111111111110110 3
b100000 7
b0 8
b10 J
b11110100001000110111 M
1O
0R
0T
0\
0]
b0 b
1c
b100 e
b1111 f
1g
b0 h
b100000 i
1x
b100 y
1{
b11100 |
b101000 ~
#90000
0-
0O
0x
0{
#95000
1#
b101000 $
1%
b11111111111111111111111111110111 &
1-
b100100 7
b0 8
b11110100001000110110 M
1O
b101000 Q
1R
b11111111111111111111111111110111 S
1T
0\
0]
b0 b
1c
b1111 f
1g
b0 h
b100100 i
1x
b100 y
1{
b100000 |
#100000
0-
0O
0x
0{
#105000
1!
1"
1-
b1111 /
b11111111111111111111111111110111 1
b1000 2
b101000 7
b0 8
b11110100001000110101 M
1O
1\
1]
b1111 b
1c
b11111111111111111111111111110111 d
b1000 e
b1111 f
1g
b0 h
b101000 i
1x
b100 y
1{
b100100 |
#110000
0-
0O
0x
0{
#115000
0!
b10111 !!
0"
0#
0%
1-
b0 /
b11111111111111111111111111110111 3
b0 7
b0 8
b11 J
b11110100001000110100 M
1O
0R
0T
0\
0]
b0 b
1c
b1000 e
b1111 f
1g
b0 h
b0 i
1l
1x
b1000 y
1{
b101000 |
b101100 ~
#120000
0-
0O
0x
0{
#125000
1#
b101100 $
1%
b10111 &
1-
b0 4
b0 8
b11110100001000110011 M
1O
b101100 Q
1R
b10111 S
1T
0\
0]
b0 b
1c
b0 f
1g
1x
b1000 y
1{
b0 |
#130000
0-
0O
0x
0{
#135000
1!
1"
1-
b1111 /
b10111 1
b1100 2
b11110100001000110010 M
1O
1\
1]
b1111 b
1c
b10111 d
b1100 e
b0 f
1g
1x
b1000 y
1{
b0 |
#140000
0-
0O
0x
0{
#145000
0!
b111000 !!
0"
0#
0%
1-
b0 /
b10111 3
b100 J
b11110100001000110001 M
1O
0R
0T
0\
0]
b0 b
1c
b1100 e
b0 f
1g
1x
b1100 y
1{
b0 |
b110000 ~
#150000
0-
0O
0x
0{
#155000
1#
b110000 $
1%
b111000 &
1-
b11110100001000110000 M
1O
b110000 Q
1R
b111000 S
1T
0\
0]
b0 b
1c
b0 f
1g
1x
b1100 y
1{
b0 |
#160000
0-
0O
0x
0{
#165000
1!
1"
1-
b1111 /
b111000 1
b10000 2
b11110100001000101111 M
1O
1\
1]
b1111 b
1c
b111000 d
b10000 e
b0 f
1g
1x
b1100 y
1{
b0 |
#170000
0-
0O
0x
0{
#175000
0!
b111111 !!
0"
0#
0%
1-
b0 /
b111000 3
b101 J
b11110100001000101110 M
1O
0R
0T
0\
0]
b0 b
1c
b10000 e
b0 f
1g
1x
b10000 y
1{
b0 |
b110100 ~
#180000
0-
0O
0x
0{
